wechaty_puppet_itchat/__init__.py
wechaty_puppet_itchat/browser.py
wechaty_puppet_itchat/config.py
wechaty_puppet_itchat/puppet.py
wechaty_puppet_itchat/utils.py
wechaty_puppet_itchat/version.py
wechaty_puppet_itchat/version_test.py
wechaty_puppet_itchat/itchat/__init__.py
wechaty_puppet_itchat/itchat/config.py
wechaty_puppet_itchat/itchat/content.py
wechaty_puppet_itchat/itchat/core.py
wechaty_puppet_itchat/itchat/log.py
wechaty_puppet_itchat/itchat/returnvalues.py
wechaty_puppet_itchat/itchat/utils.py
wechaty_puppet_itchat/itchat/async_components/__init__.py
wechaty_puppet_itchat/itchat/async_components/contact.py
wechaty_puppet_itchat/itchat/async_components/hotreload.py
wechaty_puppet_itchat/itchat/async_components/login.py
wechaty_puppet_itchat/itchat/async_components/messages.py
wechaty_puppet_itchat/itchat/async_components/register.py
wechaty_puppet_itchat/itchat/components/__init__.py
wechaty_puppet_itchat/itchat/components/contact.py
wechaty_puppet_itchat/itchat/components/hotreload.py
wechaty_puppet_itchat/itchat/components/login.py
wechaty_puppet_itchat/itchat/components/messages.py
wechaty_puppet_itchat/itchat/components/register.py
wechaty_puppet_itchat/itchat/storage/__init__.py
wechaty_puppet_itchat/itchat/storage/messagequeue.py
wechaty_puppet_itchat/itchat/storage/templates.py
wechaty_puppet_itchat-0.0.6.dist-info/LICENSE
wechaty_puppet_itchat-0.0.6.dist-info/METADATA
wechaty_puppet_itchat-0.0.6.dist-info/WHEEL
wechaty_puppet_itchat-0.0.6.dist-info/top_level.txt
wechaty_puppet_itchat-0.0.6.dist-info/RECORD
