Metadata-Version: 2.1
Name: wechaty-puppet-itchat
Version: 0.0.6
Summary: Itchat Puppet for Wechaty
Home-page: https://github.com/lyleshaw/python-wechaty-puppet-itchat
Author: Lyle Shaw
Author-email: x@lyleshaw.com
License: Apache-2.0
Platform: UNKNOWN
Classifier: Programming Language :: Python :: 3.7
Classifier: License :: OSI Approved :: Apache Software License
Classifier: Operating System :: OS Independent
Requires-Dist: pyppeteer
Requires-Dist: dataclasses-json
Requires-Dist: pyee
Requires-Dist: requests
Requires-Dist: PyQRCode
Requires-Dist: dataclasses
Requires-Dist: grpclib
Requires-Dist: wechaty
Requires-Dist: loguru
Requires-Dist: itchat-uos (==1.5.0.dev0)
Requires-Dist: node-semver (~=0.8.1)
